json2pytocol/__init__.py
json2pytocol/json_to_python_protocol.py
tests/__init__.py
tests/test_json_to_python.py
json2pytocol-0.0.4.dist-info/LICENSE
json2pytocol-0.0.4.dist-info/METADATA
json2pytocol-0.0.4.dist-info/WHEEL
json2pytocol-0.0.4.dist-info/entry_points.txt
json2pytocol-0.0.4.dist-info/top_level.txt
json2pytocol-0.0.4.dist-info/RECORD
