Metadata-Version: 2.1
Name: json2pytocol
Version: 0.0.4
Summary: Generate Python Protocol Classes From Json
Home-page: https://github.com/piacenti/json2pytocol
Author: Gabriel Piacenti
Author-email: piacenti10@gmail.com
License: UNKNOWN
Platform: UNKNOWN
Classifier: Programming Language :: Python :: 3
Classifier: License :: OSI Approved :: Apache Software License
Classifier: Operating System :: OS Independent
Requires-Python: >=3.8
Requires-Dist: dotmap
